snakelang/__init__.py
snakelang/snakelang_module.py
snakelang-0.0.3.dist-info/METADATA
snakelang-0.0.3.dist-info/WHEEL
snakelang-0.0.3.dist-info/top_level.txt
snakelang-0.0.3.dist-info/RECORD
