Metadata-Version: 2.1
Name: snakelang
Version: 0.0.3
Summary: TBD.
Author-email: Emery Berger <emery.berger@gmail.com>
Project-URL: Homepage, https://github.com/plasma-umass/snakelang
Project-URL: Bug Tracker, https://github.com/plasma-umass/snakelang/issues
Classifier: Programming Language :: Python :: 3
Classifier: License :: OSI Approved :: MIT License
Classifier: Operating System :: OS Independent
Requires-Python: >=3.7
Requires-Dist: openai (>=0.27.0)
Requires-Dist: click (>=8.1.3)
